py_jit_round_number/__init__.py
py_jit_round_number/jit_round_up_down.py
pyjitroundnumber-0.0.1.dist-info/METADATA
pyjitroundnumber-0.0.1.dist-info/WHEEL
pyjitroundnumber-0.0.1.dist-info/top_level.txt
pyjitroundnumber-0.0.1.dist-info/RECORD
