Metadata-Version: 2.1
Name: pyjitroundnumber
Version: 0.0.1
Summary: decimal number round roundup rounddown
Home-page: https://PichaiLimpanitivat@bitbucket.org/python-package/pyjitroundnumber.git
Author: PichaiLim
Author-email: Pichai.Limpanitivat@gmail.com
License: UNKNOWN
Keywords: pyJitRoundNumber jitRoundNumber decimal number round roundUp roundDown
Platform: UNKNOWN
Requires-Python: >=3.6
